agentbay/__init__.py
agentbay/_async/__init__.py
agentbay/_async/agent.py
agentbay/_async/agentbay.py
agentbay/_async/base_service.py
agentbay/_async/beta_network.py
agentbay/_async/browser.py
agentbay/_async/browser_agent.py
agentbay/_async/code.py
agentbay/_async/command.py
agentbay/_async/computer.py
agentbay/_async/context.py
agentbay/_async/context_manager.py
agentbay/_async/eval/__init__.py
agentbay/_async/eval/local_page_agent.py
agentbay/_async/eval/page_agent.py
agentbay/_async/eval/page_evals.config.json
agentbay/_async/eval/page_tasks/allrecipes.py
agentbay/_async/eval/page_tasks/apple.py
agentbay/_async/eval/page_tasks/arxiv.py
agentbay/_async/eval/page_tasks/combination_sauce.py
agentbay/_async/eval/page_tasks/extract_aigrant_companies.py
agentbay/_async/eval/page_tasks/extract_apartments.py
agentbay/_async/eval/page_tasks/extract_area_codes.py
agentbay/_async/eval/page_tasks/extract_products.py
agentbay/_async/eval/page_tasks/imdb_movie_details.py
agentbay/_async/eval/page_tasks/nonsense_action.py
agentbay/_async/eval/page_tasks/observe_amazon_add_to_cart.py
agentbay/_async/eval/page_tasks/observe_iframes1.py
agentbay/_async/eval/page_tasks/simple_google_search.py
agentbay/_async/eval/page_tasks/vanta_h.py
agentbay/_async/eval/pyproject.toml
agentbay/_async/eval/run_page_evals.py
agentbay/_async/eval/service.py
agentbay/_async/extension.py
agentbay/_async/filesystem.py
agentbay/_async/fingerprint.py
agentbay/_async/mobile.py
agentbay/_async/mobile_simulate.py
agentbay/_async/oss.py
agentbay/_async/session.py
agentbay/_common/__init__.py
agentbay/_common/config.py
agentbay/_common/enums.py
agentbay/_common/exceptions.py
agentbay/_common/logger.py
agentbay/_common/models/__init__.py
agentbay/_common/models/agent.py
agentbay/_common/models/browser.py
agentbay/_common/models/browser_agent.py
agentbay/_common/models/code.py
agentbay/_common/models/command.py
agentbay/_common/models/computer.py
agentbay/_common/models/context.py
wuying_agentbay_sdk-0.15.0.dist-info/METADATA
wuying_agentbay_sdk-0.15.0.dist-info/WHEEL
wuying_agentbay_sdk-0.15.0.dist-info/RECORD
