Metadata-Version: 2.4
Name: wuying-agentbay-sdk
Version: 0.15.0
Summary: Python SDK for interacting with the Wuying AgentBay cloud runtime environment
License: Apache-2.0
Author: Wuying AI Team
Author-email: wuying-ai-team@alibabacloud.com
Requires-Python: >=3.10,<4.0
Classifier: Development Status :: 4 - Beta
Classifier: Intended Audience :: Developers
Classifier: License :: OSI Approved :: Apache Software License
Classifier: Programming Language :: Python :: 3
Classifier: Programming Language :: Python :: 3.10
Classifier: Programming Language :: Python :: 3.11
Classifier: Programming Language :: Python :: 3.12
Classifier: Programming Language :: Python :: 3.13
Classifier: Programming Language :: Python :: 3.14
Classifier: Topic :: Software Development :: Libraries
Requires-Dist: alibabacloud-tea-openapi (>=0.4.0rc3)
Requires-Dist: alibabacloud-tea-util (>=0.3.13,<0.4.0)
Requires-Dist: aliyun-log-python-sdk (>=0.8.0,<0.9.0)
Requires-Dist: cryptography (>=44.0.0)
Requires-Dist: darabonba-core (>=1.0.0,<2.0.0)
Requires-Dist: httpx (>=0.28.1,<0.29.0)
Requires-Dist: loguru (>=0.7.0,<0.8.0)
Requires-Dist: playwright (>=1.5.0)
Requires-Dist: pydantic (>=2.0,<3.0)
Requires-Dist: python-dotenv (>=1.0.0,<2.0.0)
Project-URL: Documentation, https://github.com/aliyun/wuying-agentbay-sdk/docs
Project-URL: Homepage, https://github.com/aliyun/wuying-agentbay-sdk
Project-URL: Repository, https://github.com/aliyun/wuying-agentbay-sdk
